{
  "main": {
    "id": "8f54690c780938ed",
    "type": "split",
    "children": [
      {
        "id": "235ff74cb7652621",
        "type": "tabs",
        "children": [
          {
            "id": "c9cca1f82321bd6a",
            "type": "leaf",
            "state": {
              "type": "markdown",
              "state": {
                "file": "Spaces/Home/AWS/1. RDS Provisioning.md",
                "mode": "source",
                "backlinks": true,
                "source": false
              }
            }
          },
          {
            "id": "e0275514481c55be",
            "type": "leaf",
            "state": {
              "type": "image",
              "state": {
                "file": "Images/rds9.png"
              }
            }
          },
          {
            "id": "8fcbbc31444da6bf",
            "type": "leaf",
            "state": {
              "type": "image",
              "state": {
                "file": "Images/rds8.png"
              }
            }
          },
          {
            "id": "d92900846d487fa2",
            "type": "leaf",
            "state": {
              "type": "image",
              "state": {
                "file": "Images/rds7.png"
              }
            }
          }
        ]
      }
    ],
    "direction": "vertical"
  },
  "left": {
    "id": "7a4764dcc17a17ce",
    "type": "split",
    "children": [
      {
        "id": "a41babed7bd5cb42",
        "type": "tabs",
        "children": [
          {
            "id": "599941f4b5edb2ac",
            "type": "leaf",
            "state": {
              "type": "file-explorer",
              "state": {
                "sortOrder": "alphabetical"
              }
            }
          },
          {
            "id": "e0705d70457345ec",
            "type": "leaf",
            "state": {
              "type": "search",
              "state": {
                "query": "",
                "matchingCase": true,
                "explainSearch": false,
                "collapseAll": false,
                "extraContext": false,
                "sortOrder": "alphabetical"
              }
            }
          },
          {
            "id": "37305db5ac14c888",
            "type": "leaf",
            "state": {
              "type": "bookmarks",
              "state": {}
            }
          },
          {
            "id": "f3e163b26c384178",
            "type": "leaf",
            "state": {
              "type": "mk-file-view",
              "state": {}
            }
          }
        ],
        "currentTab": 3
      }
    ],
    "direction": "horizontal",
    "width": 300
  },
  "right": {
    "id": "82898550b926828e",
    "type": "split",
    "children": [
      {
        "id": "bb04911ec70feb23",
        "type": "tabs",
        "children": [
          {
            "id": "68faea92f12f1597",
            "type": "leaf",
            "state": {
              "type": "backlink",
              "state": {
                "file": "Spaces/Home/AWS/1. RDS Provisioning.md",
                "collapseAll": true,
                "extraContext": false,
                "sortOrder": "alphabetical",
                "showSearch": true,
                "searchQuery": "",
                "backlinkCollapsed": false,
                "unlinkedCollapsed": false
              }
            }
          },
          {
            "id": "30d4f7114828ff1a",
            "type": "leaf",
            "state": {
              "type": "tag",
              "state": {
                "sortOrder": "frequency",
                "useHierarchy": true
              }
            }
          },
          {
            "id": "7b4d35e781c1aaaa",
            "type": "leaf",
            "state": {
              "type": "outline",
              "state": {
                "file": "Spaces/Home/AWS/1. RDS Provisioning.md"
              }
            }
          },
          {
            "id": "7af23b852e8bfd12",
            "type": "leaf",
            "state": {
              "type": "outgoing-link",
              "state": {
                "file": "Spaces/Home/AWS/1. RDS Provisioning.md",
                "linksCollapsed": true,
                "unlinkedCollapsed": true
              }
            }
          },
          {
            "id": "f008d266a9a18573",
            "type": "leaf",
            "state": {
              "type": "advanced-tables-toolbar",
              "state": {}
            }
          },
          {
            "id": "b7d067efa8d71b04",
            "type": "leaf",
            "state": {
              "type": "calendar",
              "state": {}
            }
          }
        ],
        "currentTab": 4
      }
    ],
    "direction": "horizontal",
    "width": 304.5
  },
  "left-ribbon": {
    "hiddenItems": {
      "switcher:퀵 스위처 열기": false,
      "canvas:새 캔버스 만들기": false,
      "templates:템플릿 삽입": false,
      "daily-notes:오늘의 데일리 노트 열기": false,
      "graph:그래프 뷰 열기": false,
      "command-palette:명령어 팔레트 열기": false,
      "obsidian-excalidraw-plugin:Create new drawing": false,
      "table-editor-obsidian:Advanced Tables Toolbar": false
    }
  },
  "active": "c9cca1f82321bd6a",
  "lastOpenFiles": [
    "Images/rds9.png",
    "Spaces/Home/AWS/1. RDS Provisioning.md",
    "Images/rds8.png",
    "Images/rds7.png",
    "Images/rds6.png",
    "Images/rds5.png",
    "Images/rds4.png",
    "Images/rds3.png",
    "Images/rds2.png",
    "Spaces/Home/AWS/2 Blue Green Deployment in RDS fffcadd3326981e597b3dc1bdb929379.md",
    "Images/rds1.png",
    "Images/image 10.avif",
    "Images/image 9.avif",
    "Spaces/Home/Spring/Theme/Theme.md",
    "Spaces/Home/AWS",
    "Spaces/Home/Java Script/Node.js/Project/api 연동 후 DB Insert.md",
    "Spaces/Home/Spring/Theme",
    "Spaces/Home/Spring/Spring Legacy/Tiles/tiles.md",
    "Spaces/Home/Spring/Maven/Maven.md",
    "Spaces/Home/Spring/Spring Legacy/Tiles",
    "Spaces/Home/Spring/Security.md",
    "Spaces/Home/Spring/Spring Legacy 와 Spring Boot  차이.md",
    "Spaces/Home/Spring/Spring Framework.md",
    "Spaces/Home/Spring/Filter.md",
    "Spaces/Home/Network/Server&Client.md",
    "File/springframework_setting-main.zip",
    "Spaces/Home/Java Script/Node.js/Project/Node.js 프로젝트 파일.md",
    "daily note/2024/9/2024-09-25.md",
    "Spaces/Home/Java/Exception/Exception.md",
    "Spaces/Home/DB/PostGre.md",
    "daily note/2024/9/2024-09-24.md",
    "Spaces/Home/WebView/WebView.md",
    "Spaces/Home/Docker/Docker설치&명령어.md",
    "Spaces/Home/WebView",
    "Spaces/Home/DB/PostgreSql.md",
    "Spaces/Home/DB/SQL Injection.md",
    "Spaces/Cafe24/workspace/cafe24 node.js 프로젝트 파일.md",
    "Spaces/Cafe24/workspace/Cafe24 Authorization Code &PostMan & Access Token.md",
    "Spaces/Cafe24/workspace/Cafe24 플러그인 적용.md",
    "Spaces/Cafe24/workspace/Cafe24 Access Token.md",
    "Spaces/Cafe24/workspace/Cafe24 API 종류/무제 파일.md",
    "Images/Exception",
    "Images/vscode",
    "Spaces/Home/Java Script/Node.js/Project",
    "Spaces/Home/Java Script/Node.js/Node",
    "Spaces/Home/Java Script/Node.js/Module",
    "무제 파일.canvas"
  ]
}