{
  "main": {
    "id": "8f54690c780938ed",
    "type": "split",
    "children": [
      {
        "id": "d3293f863b3d5e60",
        "type": "tabs",
        "children": [
          {
            "id": "ed2adfb14b7d9c37",
            "type": "leaf",
            "state": {
              "type": "markdown",
              "state": {
                "file": "Spaces/Home/Protocol/Http/WebSocket.md",
                "mode": "source",
                "backlinks": true,
                "source": false
              }
            }
          }
        ]
      }
    ],
    "direction": "vertical"
  },
  "left": {
    "id": "7a4764dcc17a17ce",
    "type": "split",
    "children": [
      {
        "id": "a41babed7bd5cb42",
        "type": "tabs",
        "children": [
          {
            "id": "599941f4b5edb2ac",
            "type": "leaf",
            "state": {
              "type": "file-explorer",
              "state": {
                "sortOrder": "alphabetical"
              }
            }
          },
          {
            "id": "e0705d70457345ec",
            "type": "leaf",
            "state": {
              "type": "search",
              "state": {
                "query": "",
                "matchingCase": true,
                "explainSearch": false,
                "collapseAll": false,
                "extraContext": false,
                "sortOrder": "alphabetical"
              }
            }
          },
          {
            "id": "37305db5ac14c888",
            "type": "leaf",
            "state": {
              "type": "bookmarks",
              "state": {}
            }
          },
          {
            "id": "f3e163b26c384178",
            "type": "leaf",
            "state": {
              "type": "mk-file-view",
              "state": {}
            }
          }
        ]
      }
    ],
    "direction": "horizontal",
    "width": 300
  },
  "right": {
    "id": "82898550b926828e",
    "type": "split",
    "children": [
      {
        "id": "bb04911ec70feb23",
        "type": "tabs",
        "children": [
          {
            "id": "68faea92f12f1597",
            "type": "leaf",
            "state": {
              "type": "backlink",
              "state": {
                "file": "Spaces/Home/Protocol/Http/WebSocket.md",
                "collapseAll": true,
                "extraContext": false,
                "sortOrder": "alphabetical",
                "showSearch": true,
                "searchQuery": "",
                "backlinkCollapsed": false,
                "unlinkedCollapsed": false
              }
            }
          },
          {
            "id": "30d4f7114828ff1a",
            "type": "leaf",
            "state": {
              "type": "tag",
              "state": {
                "sortOrder": "frequency",
                "useHierarchy": true
              }
            }
          },
          {
            "id": "7b4d35e781c1aaaa",
            "type": "leaf",
            "state": {
              "type": "outline",
              "state": {
                "file": "Spaces/Home/Protocol/Http/WebSocket.md"
              }
            }
          },
          {
            "id": "7af23b852e8bfd12",
            "type": "leaf",
            "state": {
              "type": "outgoing-link",
              "state": {
                "file": "Spaces/Home/Protocol/Http/WebSocket.md",
                "linksCollapsed": true,
                "unlinkedCollapsed": true
              }
            }
          },
          {
            "id": "f008d266a9a18573",
            "type": "leaf",
            "state": {
              "type": "advanced-tables-toolbar",
              "state": {}
            }
          },
          {
            "id": "b7d067efa8d71b04",
            "type": "leaf",
            "state": {
              "type": "calendar",
              "state": {}
            }
          }
        ],
        "currentTab": 4
      }
    ],
    "direction": "horizontal",
    "width": 301.5
  },
  "left-ribbon": {
    "hiddenItems": {
      "switcher:퀵 스위처 열기": false,
      "canvas:새 캔버스 만들기": false,
      "templates:템플릿 삽입": false,
      "daily-notes:오늘의 데일리 노트 열기": false,
      "graph:그래프 뷰 열기": false,
      "command-palette:명령어 팔레트 열기": false,
      "obsidian-excalidraw-plugin:Create new drawing": false,
      "table-editor-obsidian:Advanced Tables Toolbar": false
    }
  },
  "active": "ed2adfb14b7d9c37",
  "lastOpenFiles": [
    "Spaces/Home/Protocol/Http/HTTPS(HTTP와 차이점).md",
    "Spaces/Home/Protocol/Http/Socekt.md",
    "Spaces/Home/Protocol/Http/SSE.md",
    "Spaces/Home/Protocol/Http/STOMP.md",
    "Spaces/Home/Protocol/Http/WebSocket.md",
    "daily note/2024-01-08.md",
    "daily note/2024-01-03.md",
    "Spaces/Home/Tomcat/Smart Tomcat.md",
    "Images/Smart Tomcat10.png",
    "Images/Smart Tomcat12.png",
    "Images/Smart Tomcat11.png",
    "Images/Smart Tomcat9.png",
    "Images/Smart Tomcat8.png",
    "Images/Smart Tomcat7.png",
    "Images/Smart Tomcat6.png",
    "Images/Smart Tomcat5.png",
    "Images/Smart Tomcat4.png",
    "Images/Smart Tomcat3.png",
    "Spaces/Home/Tomcat",
    "Images/Socket",
    "Images/새 폴더",
    "Spaces/Home/Protocol/Http/HTTP Polling.md",
    "Spaces/Home/Protocol/Http/Http.md",
    "Spaces/Home/Protocol/Http/SSL/SSL.md",
    "Images/WebSocket",
    "Images/Polling - 복사본",
    "Images/SSE",
    "Images/SSL",
    "Images/Quartz",
    "Images/ThreadLock",
    "Images/STOMP",
    "Spaces/Home/Java/Java DB/Statement & Prepared Statement.md",
    "Spaces/Home/Java/JVM/ThreadLock.md",
    "Spaces/Home/Java/JVM/Thread.md",
    "Spaces/Home/Java/JVM/Process.md",
    "Spaces/Home/Spring/JPA.md",
    "Spaces/Home/Spring/AOP/AOP.md",
    "Spaces/Home/Java/Sleep/Sleep.md",
    "Spaces/Home/Java/Random/Random.md",
    "Spaces/Home/Java/Scheduler/Cron.md",
    "Spaces/Home/Java/Java DB/Connection& DriverManager Class.md",
    "Spaces/Home/Java/Java DB/Java DB Connection.md",
    "Spaces/Home/Java/Java DB/Open API Insert.md",
    "Spaces/Home/Java/JVM/JVM.md",
    "Spaces/Home/Java/JVM/Garbage Collection.md",
    "Spaces/Home/Java/Java DB/Class.forName(driver).md",
    "무제 파일.canvas"
  ]
}